pressureclamp/__init__.py
pressureclamp/load_file.py
pressureclamp/plot_functions.py
pressureclamp/preprocess.py
pressureclamp/summarize.py
pressureclamp-0.1.3.dist-info/LICENSE
pressureclamp-0.1.3.dist-info/WHEEL
pressureclamp-0.1.3.dist-info/METADATA
pressureclamp-0.1.3.dist-info/RECORD
